colors_accessibility/__init__.py
colors_accessibility/accessibility_processor.py
colors_accessibility/color.py
colors_accessibility/validator.py
colors_accessibility/data/__init__.py
colors_accessibility/data/configuration_data.py
colors_accessibility/data/test_data.py
colors_accessibility/utils/__init__.py
colors_accessibility/utils/classes.py
colors_accessibility/utils/decorators.py
colors_accessibility/utils/errors.py
colors_accessibility/utils/registry.py
colors_accessibility-0.0.5.dist-info/LICENSE
colors_accessibility-0.0.5.dist-info/METADATA
colors_accessibility-0.0.5.dist-info/WHEEL
colors_accessibility-0.0.5.dist-info/top_level.txt
colors_accessibility-0.0.5.dist-info/RECORD
