Metadata-Version: 2.1
Name: colors-accessibility
Version: 0.0.5
Summary: Package to process and change colors between color spaces and to tweak input colors to meet WCAG 2.1 accessibility standards.
Home-page: https://github.com/phryniewicz/colors-accessibility
Author: Piotr Hryniewicz
Author-email: phryniewicz.dev@gmail.com
Project-URL: Bug Tracker, https://github.com/phryniewicz/colors-accessibility/issues
Classifier: Programming Language :: Python :: 3
Classifier: License :: OSI Approved :: MIT License
Classifier: Operating System :: OS Independent
Requires-Python: >=3.8
License-File: LICENSE
